LICENSE.txt
MANIFEST.in
README.rst
setup.cfg
setup.py
reqs/requires-2.6.txt
reqs/requires.txt
stage/__init__.py
stage/conf.py
stage.egg-info/PKG-INFO
stage.egg-info/SOURCES.txt
stage.egg-info/dependency_links.txt
stage.egg-info/not-zip-safe
stage.egg-info/requires.txt
stage.egg-info/top_level.txt
tests/__init__.py
tests/classconf.py
tests/test_stage.py
tests/twodeep.py